{
	"2581": {
		"pos": [0, 5.61762, -1.55519],
		"model": "carrier"
	},
	"3460": {
		"pos": [0, 6.71927, -0.918279],
		"model": "carrier"
	},
	"4": {
		"pos": [0, 13.2428, -2.78348],
		"model": "com"
	},
	"3": {
		"pos": [0, 4.08243, -1.83658],
		"model": "mil"
	},
	"7": {
		"pos": [0, 3.3, -1.83658],
		"model": "mil"
	},
	"10": {
		"pos": [0, 28.8441, -4.89455],
		"model": "com"
	},
	"18": {
		"pos": [0, 4.94153, -2.41467],
		"model": "mil"
	},
	"20": {
		"pos": [0, 15.1418, -4.17127],
		"model": "com"
	},
	"24": {
		"pos": [0, 27.2171, -4.63457],
		"model": "com"
	},
	"3575": {
		"pos": [0, 24.684, -4.49777],
		"model": "com"
	},
	"2948": {
		"pos": [0.104557, 10, -4.34851],
		"model": "mil"
	},
	"2310": {
		"pos": [0.359808, 4.23023, -2.39445],
		"model": "mil"
	},
	"2843": {
		"pos": [0, 15.6399, -4.02614],
		"model": "com"
	},
	"2899": {
		"pos": [0, 15.6399, -4.02614],
		"model": "com"
	},
	"2878": {
		"pos": [0, 12.4873, -3.99752],
		"model": "com"
	},
	"3140": {
		"pos": [0, 12.4873, -3.99752],
		"model": "com"
	},
	"2879": {
		"pos": [0, 12.4873, -3.99752],
		"model": "com"
	},
	"3534": {
		"pos": [0, 12.5936, -4.65545],
		"model": "com"
	},
	"2870": {
		"pos": [0, 12.7605, -4.53432],
		"model": "com"
	},
	"2871": {
		"pos": [0, 12.7605, -4.53432],
		"model": "com"
	},
	"2865": {
		"pos": [0, 12.7605, -4.53432],
		"model": "com"
	},
	"242": {
		"pos": [0, 15.2802, -3.70538],
		"model": "com"
	},
	"4646": {
		"pos": [0, 17.5782, -4.5311],
		"model": "com"
	},
	"244": {
		"pos": [0, 20.2257, -4.89693],
		"model": "com"
	},
	"4631": {
		"pos": [0, 19.288, -5.12993],
		"model": "com"
	},
	"2153": {
		"pos": [0, 28.017, -3.92616],
		"model": "com"
	},
	"2973": {
		"pos": [0, 28.8128, -5.53784],
		"model": "com"
	},
	"239": {
		"pos": [0, 27.4941, -3.03905],
		"model": "com"
	},
	"3011": {
		"pos": [0, 14.2946, -3.71011],
		"model": "com"
	},
	"2856": {
		"pos": [0, 15.9399, -3.90099],
		"model": "mil"
	},
	"2772": {
		"pos": [0, 14.2946, -3.71011],
		"model": "com"
	},
	"2769": {
		"pos": [0, 14.2946, -3.71011],
		"model": "com"
	},
	"4140": {
		"pos": [0, 12.6537, -2.41209],
		"model": "com"
	},
	"2003": {
		"pos": [0, 13.6095, -3.40369],
		"model": "com"
	},
	"3054": {
		"pos": [0, 14.2925, -3.71367],
		"model": "com"
	},
	"252": {
		"pos": [0, 27.8197, -4.54815],
		"model": "com"
	},
	"238": {
		"pos": [0, 16.8463, -0.922822],
		"model": "com"
	},
	"237": {
		"pos": [0, 19.4308, -3.20719],
		"model": "com"
	},
	"240": {
		"pos": [0, 27.3886, -4.85235],
		"model": "com"
	},
	"3179": {
		"pos": [0, 27.1953, -4.22552],
		"model": "com"
	},
	"3180": {
		"pos": [0, 27.1953, -4.22552],
		"model": "com"
	},
	"235": {
		"pos": [0, 22.3654, -2.14899],
		"model": "com"
	},
	"2386": {
		"pos": [0, 22.8432, -5.21989],
		"model": "com"
	},
	"3292": {
		"pos": [0, 14.2346, -3.71806],
		"model": "mil"
	},
	"3617": {
		"pos": [0, 4.66936, -1.96233],
		"model": "mil"
	},
	"2951": {
		"pos": [0, 3.25846, -1.18977],
		"model": "mil"
	},
	"3591": {
		"pos": [0.034112, 4.71232, -2.09464],
		"model": "mil"
	},
	"2857": {
		"pos": [0, 4.0179, -2.08502],
		"model": "mil"
	},
	"2556": {
		"pos": [0, 14.9541, -2.97223],
		"model": "mil"
	},
	"25": {
		"pos": [0, 27.3886, -4.53457],
		"model": "com"
	},
	"5193": {
		"pos":  [0,25.7,-4.48],
		"model": "com"
	},
	"5038": {
		"pos": [0, 15.96, -4.69],
		"model": "com"
	}
}
